mdanalysis-2.10.0.dist-info/RECORD
mdanalysis-2.10.0.dist-info/WHEEL
mdanalysis-2.10.0.dist-info/top_level.txt
mdanalysis-2.10.0.dist-info/METADATA
mdanalysis-2.10.0.dist-info/licenses/LICENSE
mdanalysis-2.10.0.dist-info/licenses/AUTHORS
doc/README
doc/sphinx/Makefile
doc/sphinx/source/index.rst
doc/sphinx/source/references.bib
doc/sphinx/source/conf.py
doc/sphinx/source/images/msd_demo_plot.png
doc/sphinx/source/images/AnalysisBase_parallel.png
doc/sphinx/source/images/rama_ref_plot.png
doc/sphinx/source/images/janin_ref_plot.png
doc/sphinx/source/images/parallelization_time.png
doc/sphinx/source/images/rama_demo_plot.png
doc/sphinx/source/images/janin_demo_plot.png
doc/sphinx/source/images/RSMD_plot.png
doc/sphinx/source/documentation_pages/coordinates_modules.rst
doc/sphinx/source/documentation_pages/auxiliary_modules.rst
doc/sphinx/source/documentation_pages/trajectory_transformations.rst
doc/sphinx/source/documentation_pages/topology.rst
doc/sphinx/source/documentation_pages/converters.rst
doc/sphinx/source/documentation_pages/overview.rst
doc/sphinx/source/documentation_pages/selections.rst
doc/sphinx/source/documentation_pages/topology_modules.rst
doc/sphinx/source/documentation_pages/references.rst
doc/sphinx/source/documentation_pages/guesser_modules.rst
doc/sphinx/source/documentation_pages/version.rst
doc/sphinx/source/documentation_pages/core_modules.rst
doc/sphinx/source/documentation_pages/lib_modules.rst
doc/sphinx/source/documentation_pages/selections_modules.rst
doc/sphinx/source/documentation_pages/analysis_modules.rst
doc/sphinx/source/documentation_pages/visualization_modules.rst
doc/sphinx/source/documentation_pages/exceptions.rst
doc/sphinx/source/documentation_pages/units.rst
doc/sphinx/source/documentation_pages/visualization/testing_streamline.png
doc/sphinx/source/documentation_pages/visualization/streamlines.rst
doc/sphinx/source/documentation_pages/visualization/streamlines_3D.rst
doc/sphinx/source/documentation_pages/visualization/test_streamplot_3D.png
doc/sphinx/source/documentation_pages/topology/ITPParser.rst
doc/sphinx/source/documentation_pages/topology/MOL2Parser.rst
