Metadata-Version: 2.4
Name: MDAnalysis
Version: 2.10.0
Summary: An object-oriented toolkit to analyze molecular dynamics trajectories.
Author-email: MDAnalysis Development Team <mdanalysis@numfocus.org>
Maintainer-email: MDAnalysis Core Developers <mdanalysis@numfocus.org>
License: ==========================================================================
Project-URL: Homepage, https://www.mdanalysis.org
Project-URL: Download, https://github.com/MDAnalysis/mdanalysis/releases
Project-URL: Documentation, https://docs.mdanalysis.org/
Project-URL: User Guide, https://userguide.mdanalysis.org/
Project-URL: Issue Tracker, https://github.com/mdanalysis/mdanalysis/issues
Project-URL: Github Discussions, https://github.com/MDAnalysis/mdanalysis/discussions
Project-URL: Discord, https://discord.com/channels/807348386012987462/
Project-URL: Blog, https://www.mdanalysis.org/blog/
Project-URL: Source, https://github.com/mdanalysis/mdanalysis
Keywords: python,science,chemistry,biophysics,molecular-dynamics,computational-chemistry,molecular-simulation,analysis,trajectory-analysis
Classifier: Development Status :: 6 - Mature
Classifier: Environment :: Console
Classifier: Intended Audience :: Science/Research
Classifier: License :: OSI Approved :: GNU Lesser General Public License v3 or later (LGPLv3+)
Classifier: Operating System :: POSIX
Classifier: Operating System :: MacOS :: MacOS X
Classifier: Operating System :: Microsoft :: Windows
Classifier: Programming Language :: Python
Classifier: Programming Language :: Python :: 3.11
Classifier: Programming Language :: Python :: 3.12
Classifier: Programming Language :: Python :: 3.13
Classifier: Programming Language :: Python :: 3.14
Classifier: Programming Language :: C
Classifier: Topic :: Scientific/Engineering
Classifier: Topic :: Scientific/Engineering :: Bio-Informatics
Classifier: Topic :: Scientific/Engineering :: Chemistry
Classifier: Topic :: Software Development :: Libraries :: Python Modules
Provides: MDAnalysis
Requires-Python: >=3.11
License-File: LICENSE
License-File: AUTHORS
Requires-Dist: numpy>=1.26.0
Requires-Dist: GridDataFormats>=0.4.0
Requires-Dist: mmtf-python>=1.0.0
Requires-Dist: joblib>=0.12
Requires-Dist: scipy>=1.5.0
Requires-Dist: matplotlib>=1.5.1
Requires-Dist: tqdm>=4.43.0
Requires-Dist: threadpoolctl
Requires-Dist: packaging
Requires-Dist: filelock
Requires-Dist: mda-xdrlib
Provides-Extra: extra-formats
Requires-Dist: netCDF4>=1.0; extra == "extra-formats"
Requires-Dist: h5py>=2.10; extra == "extra-formats"
Requires-Dist: chemfiles>=0.10; extra == "extra-formats"
Requires-Dist: parmed; extra == "extra-formats"
Requires-Dist: pyedr>=0.7.0; extra == "extra-formats"
Requires-Dist: pytng>=0.2.3; extra == "extra-formats"
Requires-Dist: gsd>3.0.0; extra == "extra-formats"
Requires-Dist: rdkit>=2022.09.1; extra == "extra-formats"
Requires-Dist: imdclient>=0.2.2; extra == "extra-formats"
Provides-Extra: analysis
Requires-Dist: biopython>=1.80; extra == "analysis"
Requires-Dist: seaborn; extra == "analysis"
Requires-Dist: scikit-learn; extra == "analysis"
Requires-Dist: tidynamics>=1.0.0; extra == "analysis"
Requires-Dist: networkx>=2.0; extra == "analysis"
Requires-Dist: waterdynamics; extra == "analysis"
Requires-Dist: pathsimanalysis; extra == "analysis"
Requires-Dist: mdahole2; extra == "analysis"
Provides-Extra: doc
Requires-Dist: sphinx; extra == "doc"
Requires-Dist: sphinx-sitemap; extra == "doc"
Requires-Dist: mdanalysis-sphinx-theme>=1.3.0; extra == "doc"
Requires-Dist: sphinxcontrib-bibtex; extra == "doc"
Requires-Dist: pybtex; extra == "doc"
Requires-Dist: pybtex-docutils; extra == "doc"
Provides-Extra: parallel
Requires-Dist: dask; extra == "parallel"
Dynamic: description
Dynamic: description-content-type
Dynamic: license-file
Dynamic: provides
